streamlord/__init__.py
streamlord/collectors/__init__.py
streamlord/collectors/navigation.py
streamlord/definitions/__init__.py
streamlord/definitions/contracts.py
streamlord/pipeline.py
streamlord/transformers/__init__.py
streamlord/transformers/destroyer.py
streamlord/transformers/digger.py
streamlord/transformers/injector.py
streamlord/transformers/squeezer.py
streamlord/transformers/stamper.py
streamlord/unions/__init__.py
streamlord/unions/m2o.py
streamlord-0.3.0.dist-info/METADATA
streamlord-0.3.0.dist-info/WHEEL
streamlord-0.3.0.dist-info/RECORD
