Metadata-Version: 2.1
Name: streamlord
Version: 0.3.0
Summary: Collection of tools to manipulate data streams
Home-page: https://github.com/smairon/streamlord
Author: Smairon
Author-email: man@smairon.ru
Requires-Python: >=3.11,<4.0
Classifier: Programming Language :: Python :: 3
Classifier: Programming Language :: Python :: 3.11
Classifier: Programming Language :: Python :: 3.12
Project-URL: Repository, https://github.com/smairon/streamlord
